{
	"difficulty_level": "HARD",
	"questions": [
		{
			"question": "What day is it",
			"options": ["Day A", "Day B", "Day C", "Day D"]
		},
		{
			"question": "What day is it",
			"options": ["Day A", "Day B", "Day C", "Day D"]
		},
		{
			"question": "What day is it",
			"options": ["Day A", "Day B", "Day C", "Day D"]
		},
		{
			"question": "What day is it",
			"options": ["Day A", "Day B", "Day C", "Day D"]
		},
		{
			"question": "What day is it",
			"options": ["Day A", "Day B", "Day C", "Day D"]
		},
		{
			"question": "What day is it",
			"options": ["Day A", "Day B", "Day C", "Day D"]
		},
		{
			"question": "What day is it",
			"options": ["Day A", "Day B", "Day C", "Day D"]
		},
		{
			"question": "What day is it",
			"options": ["Day A", "Day B", "Day C", "Day D"]
		},
		{
			"question": "What day is it",
			"options": ["Day A", "Day B", "Day C", "Day D"]
		},
		{
			"question": "What day is it",
			"options": ["Day A", "Day B", "Day C", "Day D"]
		},
		{
			"question": "What day is it",
			"options": ["Day A", "Day B", "Day C", "Day D"]
		},
		{
			"question": "What day is it",
			"options": ["Day A", "Day B", "Day C", "Day D"]
		},
		{
			"question": "What day is it",
			"options": ["Day A", "Day B", "Day C", "Day D"]
		},
		{
			"question": "What day is it",
			"options": ["Day A", "Day B", "Day C", "Day D"]
		},
		{
			"question": "What day is it",
			"options": ["Day A", "Day B", "Day C", "Day D"]
		},
		{
			"question": "What day is it",
			"options": ["Day A", "Day B", "Day C", "Day D"]
		},
		{
			"question": "What day is it",
			"options": ["Day A", "Day B", "Day C", "Day D"]
		},
		{
			"question": "What day is it",
			"options": ["Day A", "Day B", "Day C", "Day D"]
		},
		{
			"question": "What day is it",
			"options": ["Day A", "Day B", "Day C", "Day D"]
		},
		{
			"question": "What day is it",
			"options": ["Day A", "Day B", "Day C", "Day D"]
		}
	],
	"keys": [
		"A",
		"B",
		"C",
		"D",
		"A",
		"B",
		"C",
		"D",
		"A",
		"B",
		"C",
		"D",
		"A",
		"B",
		"C",
		"D",
		"A",
		"B",
		"C",
		"D"
	]
}
